CHANGELOG.txt
LICENSE.txt
MANIFEST.in
README.txt
__init__.py
custom_logger.py
enums.py
main.py
my_custom_logs.txt
setup.py
mylogginglibrary.egg-info/PKG-INFO
mylogginglibrary.egg-info/SOURCES.txt
mylogginglibrary.egg-info/dependency_links.txt
mylogginglibrary.egg-info/top_level.txt