Metadata-Version: 2.1
Name: mylogginglibrary
Version: 0.0.1
Summary: A library with basic features for logging
Home-page: 
Author: Cyborg Sharks team
Author-email: oryn.bay505@gmail.com
License: MIT
Platform: UNKNOWN
Classifier: Development Status :: 5 - Production/Stable
Classifier: Intended Audience :: Education
Classifier: Operating System :: Microsoft :: Windows :: Windows 10
Classifier: License :: OSI Approved :: MIT License
Classifier: Programming Language :: Python :: 3
License-File: LICENSE.txt
